odoo/addons/contract_sale_tag/README.rst
odoo/addons/contract_sale_tag/__init__.py
odoo/addons/contract_sale_tag/__manifest__.py
odoo/addons/contract_sale_tag/i18n/contract_sale_tag.pot
odoo/addons/contract_sale_tag/models/__init__.py
odoo/addons/contract_sale_tag/models/contract_contract.py
odoo/addons/contract_sale_tag/models/sale_order.py
odoo/addons/contract_sale_tag/readme/CONTRIBUTORS.rst
odoo/addons/contract_sale_tag/readme/DESCRIPTION.rst
odoo/addons/contract_sale_tag/setup/.setuptools-odoo-make-default-ignore
odoo/addons/contract_sale_tag/setup/README
odoo/addons/contract_sale_tag/static/description/icon.png
odoo/addons/contract_sale_tag/static/description/index.html
odoo/addons/contract_sale_tag/tests/__init__.py
odoo/addons/contract_sale_tag/tests/common.py
odoo/addons/contract_sale_tag/tests/test_contract_sale_tag.py
odoo/addons/contract_sale_tag/views/sale_order.xml
odoo14_addon_contract_sale_tag-14.0.1.0.1.dist-info/METADATA
odoo14_addon_contract_sale_tag-14.0.1.0.1.dist-info/WHEEL
odoo14_addon_contract_sale_tag-14.0.1.0.1.dist-info/top_level.txt
odoo14_addon_contract_sale_tag-14.0.1.0.1.dist-info/RECORD
